yatracker_linker/__init__.py
yatracker_linker/__main__.py
yatracker_linker/args.py
yatracker_linker/deps.py
yatracker_linker/gitlab_client.py
yatracker_linker/service.py
yatracker_linker/tracker_client.py
yatracker_linker/utils.py
yatracker_linker/views/__init__.py
yatracker_linker/views/base.py
yatracker_linker/views/events.py
yatracker_linker/views/proxy.py
yatracker_linker-0.3.8.dist-info/LICENSE
yatracker_linker-0.3.8.dist-info/METADATA
yatracker_linker-0.3.8.dist-info/WHEEL
yatracker_linker-0.3.8.dist-info/entry_points.txt
yatracker_linker-0.3.8.dist-info/RECORD
