Metadata-Version: 2.1
Name: yatracker-linker
Version: 0.3.8
Summary: Yandex Tracker issues integration
License: MIT
Author: Alexander Vasin
Author-email: hi@alvass.in
Requires-Python: >=3.10,<4.0
Classifier: License :: OSI Approved :: MIT License
Classifier: Programming Language :: Python :: 3
Classifier: Programming Language :: Python :: 3.10
Classifier: Programming Language :: Python :: 3.11
Requires-Dist: aiohttp (>=3.8.4,<4.0.0)
Requires-Dist: aiomisc-dependency (>=0.1.17,<0.2.0)
Requires-Dist: aiomisc[raven] (>=17.0.9,<18.0.0)
Requires-Dist: argclass (>=0.9.2,<0.10.0)
Requires-Dist: pydantic (>=1.10.7,<2.0.0)
Requires-Dist: yarl (>=1.8.2,<2.0.0)
